setup.py
chappie/__init__.py
chappie/machine.py
chappie.egg-info/PKG-INFO
chappie.egg-info/SOURCES.txt
chappie.egg-info/dependency_links.txt
chappie.egg-info/not-zip-safe
chappie.egg-info/top_level.txt