Metadata-Version: 1.0
Name: chappie
Version: 0.0.1
Summary: Minimal Finite State Machine
Home-page: https://github.com/frodsan/chappie
Author: Francesco Rodríguez
Author-email: frodsan@protonmail.com
License: MIT
Platform: UNKNOWN
